README.md
setup.py
pypif_sdk/__init__.py
pypif_sdk/accessor.py
pypif_sdk.egg-info/PKG-INFO
pypif_sdk.egg-info/SOURCES.txt
pypif_sdk.egg-info/dependency_links.txt
pypif_sdk.egg-info/requires.txt
pypif_sdk.egg-info/top_level.txt
pypif_sdk/func/__init__.py
pypif_sdk/func/calculate_funcs.py
pypif_sdk/func/copy_funcs.py
pypif_sdk/func/elements.json
pypif_sdk/func/replace_funcs.py
pypif_sdk/func/update_funcs.py
pypif_sdk/interop/__init__.py
pypif_sdk/interop/datacite.py
pypif_sdk/interop/mdf.py
pypif_sdk/readview/__init__.py
pypif_sdk/readview/core.py
pypif_sdk/util/__init__.py
pypif_sdk/util/citrination.py