Metadata-Version: 1.0
Name: pypif-sdk
Version: 2.3.0
Summary: High level support for working with Physical Information Files (PIF)
Home-page: http://github.com/CitrineInformatics/pypif-sdk
Author: Max Hutchinson
Author-email: maxhutch@citrine.io
License: UNKNOWN
Platform: UNKNOWN
